README
setup.py
txRDQ.egg-info/PKG-INFO
txRDQ.egg-info/SOURCES.txt
txRDQ.egg-info/dependency_links.txt
txRDQ.egg-info/requires.txt
txRDQ.egg-info/top_level.txt
txrdq/__init__.py
txrdq/dpq.py
txrdq/job.py
txrdq/pool.py
txrdq/rdq.py
txrdq/test/__init__.py
txrdq/test/test_dpq.py
txrdq/test/test_job.py
txrdq/test/test_pool.py
txrdq/test/test_rdq.py