Metadata-Version: 1.1
Name: txRDQ
Version: 0.2.14
Summary: A Twisted class for queueing and dispatching jobs in a controlled manner.
Home-page: https://launchpad.net/txrdq
Author: Fluidinfo Inc.
Author-email: info@fluidinfo.com
License: UNKNOWN
Download-URL: https://code.launchpad.net/txrdq
Keywords: twisted dispatch job queue
Platform: UNKNOWN
Classifier: Programming Language :: Python
Classifier: Framework :: Twisted
Classifier: Development Status :: 4 - Beta
Classifier: Intended Audience :: Developers
Classifier: License :: OSI Approved :: Apache Software License
Classifier: Operating System :: OS Independent
Classifier: Topic :: Software Development :: Libraries :: Python Modules
Provides: txrdq
